ezdevice/__init__.py
ezdevice/__main__.py
ezdevice/client.py
ezdevice-0.0.7.dist-info/DESCRIPTION.rst
ezdevice-0.0.7.dist-info/METADATA
ezdevice-0.0.7.dist-info/RECORD
ezdevice-0.0.7.dist-info/WHEEL
ezdevice-0.0.7.dist-info/entry_points.txt
ezdevice-0.0.7.dist-info/metadata.json
ezdevice-0.0.7.dist-info/top_level.txt
