Metadata-Version: 2.0
Name: ezdevice
Version: 0.0.7
Summary: Python tool & library for using ESP32 based Ezdevice.net projects
Home-page: https://github.com/geeksville/ezdevice-python
Author: Kevin Hester
Author-email: kevinh@geeksville.com
License: MIT
Platform: UNKNOWN
Classifier: License :: OSI Approved :: MIT License
Classifier: Programming Language :: Python :: 3
Classifier: Programming Language :: Python :: 3.7
Requires-Python: >=3
Requires-Dist: esptool
Requires-Dist: requests
